gramapi/__init__.py
gramapi-1.0.3.dist-info/METADATA
gramapi-1.0.3.dist-info/WHEEL
gramapi-1.0.3.dist-info/top_level.txt
gramapi-1.0.3.dist-info/RECORD
